fix_commbank_ofx.py
fix_commbank_ofx-0.1.3.dist-info/METADATA
fix_commbank_ofx-0.1.3.dist-info/WHEEL
fix_commbank_ofx-0.1.3.dist-info/entry_points.txt
fix_commbank_ofx-0.1.3.dist-info/licenses/LICENSE
fix_commbank_ofx-0.1.3.dist-info/RECORD
