Metadata-Version: 2.4
Name: fix-commbank-ofx
Version: 0.1.3
Summary: Fix Commbank OFX files
Project-URL: Homepage, https://gitlab.com/daviewales/fix-commbank-ofx/
Project-URL: Repository, https://gitlab.com/daviewales/fix-commbank-ofx/
Project-URL: Issues, https://gitlab.com/daviewales/fix-commbank-ofx/-/issues
Author-email: David Wales <daviewales@disroot.org>
Maintainer-email: David Wales <daviewales@disroot.org>
License-Expression: MIT
License-File: LICENSE
Keywords: Commonwealth Bank,commbank,ofx
Requires-Python: >=3.9
Requires-Dist: ofxtools>=0.9.5
